bareasgi_graphql_next/__init__.py
bareasgi_graphql_next/controller.py
bareasgi_graphql_next/graphene/__init__.py
bareasgi_graphql_next/graphene/controller.py
bareasgi_graphql_next/graphene/helpers.py
bareasgi_graphql_next/graphene/websocket_handler.py
bareasgi_graphql_next/graphene/websocket_instance.py
bareasgi_graphql_next/graphql/__init__.py
bareasgi_graphql_next/graphql/controller.py
bareasgi_graphql_next/graphql/helpers.py
bareasgi_graphql_next/graphql/websocket_handler.py
bareasgi_graphql_next/graphql/websocket_instance.py
bareasgi_graphql_next/py.typed
bareasgi_graphql_next/template.py
bareasgi_graphql_next/utils.py
bareasgi_graphql_next/websocket_instance.py
bareasgi_graphql_next-5.0.4.dist-info/LICENSE
bareasgi_graphql_next-5.0.4.dist-info/WHEEL
bareasgi_graphql_next-5.0.4.dist-info/METADATA
bareasgi_graphql_next-5.0.4.dist-info/RECORD
