Metadata-Version: 2.1
Name: bareasgi-graphql-next
Version: 5.0.4
Summary: GraphQL support for the bareASGI framework
Home-page: https://github.com/rob-blackbourn/bareasgi-graphql-next
License: Apache-2.0
Author: Rob Blackbourn
Author-email: rob.blackbourn@gmail.com
Requires-Python: >=3.8,<4.0
Classifier: License :: OSI Approved :: Apache Software License
Classifier: Programming Language :: Python :: 3
Classifier: Programming Language :: Python :: 3.10
Classifier: Programming Language :: Python :: 3.8
Classifier: Programming Language :: Python :: 3.9
Provides-Extra: graphene
Requires-Dist: bareASGI (>=4.0.0,<5.0.0)
Requires-Dist: graphene (>=3.0,<4.0); extra == "graphene"
Requires-Dist: graphql-core (>=3.1,<4.0)
Project-URL: Repository, https://github.com/rob-blackbourn/bareasgi-graphql-next
